browser/__init__.py
browser/aio/__init__.py
browser/ajax/__init__.py
browser/html/__init__.py
browser/local_storage/__init__.py
browser/markdown/__init__.py
browser/object_storage/__init__.py
browser/session_storage/__init__.py
browser/svg/__init__.py
browser/template/__init__.py
browser/timer/__init__.py
browser/webcomponent/__init__.py
browser/websocket/__init__.py
browser/widgets/__init__.py
browser/widgets/dialog/__init__.py
browser/widgets/menu/__init__.py
browser/window/__init__.py
browser/worker/__init__.py
mockbrython-0.0.3.dist-info/LICENSE
mockbrython-0.0.3.dist-info/METADATA
mockbrython-0.0.3.dist-info/WHEEL
mockbrython-0.0.3.dist-info/top_level.txt
mockbrython-0.0.3.dist-info/RECORD
