Metadata-Version: 2.1
Name: mockbrython
Version: 0.0.3
Summary: Mock brython functions for local testing and debugging.
Home-page: https://github.com/wapringle/mockbrython
Author: Bill Pringle
Author-email: bllprngl@gmail.com
License: UNKNOWN
Platform: UNKNOWN
Classifier: Programming Language :: Python :: 3
Classifier: License :: OSI Approved :: MIT License
Classifier: Operating System :: OS Independent
Requires-Python: >=3.4
